Metadata-Version: 2.1
Name: InvoiceCrafty
Version: 1.0.0
Summary: This package can be used to convert Excel data of invoices to PDF invoices.
Home-page: https://venkateshportfolio.streamlit.app/
Author: Jajula Sai Venkatesh
Author-email: saivenkatesh619@gmail.com
License: MIT
Keywords: invoice,excel,pdf
Platform: UNKNOWN
Classifier: Development Status :: 3 - Alpha
Classifier: Intended Audience :: Developers
Classifier: Topic :: Software Development :: Build Tools
Classifier: License :: OSI Approved :: MIT License
Classifier: Programming Language :: Python :: 3.8
Classifier: Programming Language :: Python :: 3.9
Classifier: Programming Language :: Python :: 3.10
Classifier: Programming Language :: Python :: 3.11
